<?xml version="1.0" encoding="utf-8" ?><dwsync><file name="DocumentWriter.php" server="deltabusinessapplications.com//" local="3438555224" remote="3504046800" Dst="-1" /><file name="StreamWriter.php" server="deltabusinessapplications.com//" local="3438555224" remote="3504046800" Dst="-1" /><file name="DocumentWriter.php" server="ftp.perceptioneyewear.com/public_html/" local="3438555224" remote="3507597775" Dst="-1" /><file name="StreamWriter.php" server="ftp.perceptioneyewear.com/public_html/" local="3438555224" remote="3507597775" Dst="-1" /><file name="DocumentWriter.php" server="deltabusinessapplications.com" local="3438555224" remote="3510023520" Dst="-1" /><file name="StreamWriter.php" server="deltabusinessapplications.com" local="3438555224" remote="3510023520" Dst="-1" /><file name="DocumentWriter.php" server="ftp.perceptionsun.com//home/perceptsun/public_html/" local="3438555224" remote="3510316047" Dst="-1" /><file name="StreamWriter.php" server="ftp.perceptionsun.com//home/perceptsun/public_html/" local="3438555224" remote="3510316047" Dst="-1" /></dwsync>